discolytics/__init__.py
discolytics/core.py
discolytics-2.0.2.dist-info/LICENSE
discolytics-2.0.2.dist-info/METADATA
discolytics-2.0.2.dist-info/WHEEL
discolytics-2.0.2.dist-info/top_level.txt
discolytics-2.0.2.dist-info/RECORD
