Metadata-Version: 2.1
Name: discolytics
Version: 2.0.2
Summary: Core python library for interfacing with Discolytics APIs
Home-page: https://github.com/discolytics/discolytics-pycore
Author: Discolytics
Author-email: collin@discolytics.com
Requires-Python: >=3.6
License-File: LICENSE
Requires-Dist: numpy >=1.19.2
Requires-Dist: requests >=2.24.0
Requires-Dist: pandas >=1.1.3
